hanerma/__init__.py
hanerma/core.py
hanerma-1.0.1.dist-info/METADATA
hanerma-1.0.1.dist-info/WHEEL
hanerma-1.0.1.dist-info/top_level.txt
hanerma-1.0.1.dist-info/RECORD
