Metadata-Version: 2.4
Name: hanerma
Version: 1.0.1
Summary: Hierarchical Atomic Nested External Reasoning and Memory Architecture
Author: Your Name
Requires-Python: >=3.8
Requires-Dist: requests
Requires-Dist: numpy
Requires-Dist: sentence-transformers>=2.2.0
Requires-Dist: torch
Dynamic: requires-python
